kisiac/__init__.py
kisiac/check.py
kisiac/cli.py
kisiac/common.py
kisiac/config.py
kisiac/encryption.py
kisiac/filesystems.py
kisiac/lvm.py
kisiac/runtime_settings.py
kisiac/update.py
kisiac/users.py
kisiac/files/kisiac.sh.j2
kisiac-1.4.1.dist-info/METADATA
kisiac-1.4.1.dist-info/WHEEL
kisiac-1.4.1.dist-info/entry_points.txt
kisiac-1.4.1.dist-info/licenses/LICENSE
kisiac-1.4.1.dist-info/RECORD
