Metadata-Version: 2.4
Name: kisiac
Version: 1.4.1
Author-email: Johannes Koester <johannes.koester@uni-due.de>
License-File: LICENSE
Requires-Python: >=3.11
Requires-Dist: gitpython<4,>=3.1.45
Requires-Dist: humanfriendly<11,>=10.0
Requires-Dist: inquirer<4,>=3.4.1
Requires-Dist: jinja2<4,>=3.1.6
Requires-Dist: pyfstab<0.3,>=0.2.0
Requires-Dist: pyyaml<7,>=6.0.3
Requires-Dist: yte<2,>=1.9.0
